{
  "project_info": {
    "project_number": "978957335077",
    "firebase_url": "https://planter-ai-default-rtdb.firebaseio.com",
    "project_id": "planter-ai",
    "storage_bucket": "planter-ai.appspot.com"
  },
  "client": [
    {
      "client_info": {
        "mobilesdk_app_id": "1:978957335077:android:f1631405d2a2d202875dcc",
        "android_client_info": {
          "package_name": "com.DefaultCompany.PlanterAI"
        }
      },
      "oauth_client": [
        {
          "client_id": "978957335077-1tl744ei1oarmhtesp6ae5stm6olf6ct.apps.googleusercontent.com",
          "client_type": 3
        }
      ],
      "api_key": [
        {
          "current_key": "AIzaSyDH4rnDxd2zZSbOafLGsVISnWwD_kEUsBo"
        }
      ],
      "services": {
        "appinvite_service": {
          "other_platform_oauth_client": [
            {
              "client_id": "978957335077-1tl744ei1oarmhtesp6ae5stm6olf6ct.apps.googleusercontent.com",
              "client_type": 3
            }
          ]
        }
      }
    }
  ],
  "configuration_version": "1"
}